CHANGELOG.rst
CONTRIBUTING.rst
LICENSE
README.md
action_completer/__init__.py
action_completer/completer.py
action_completer/types.py
action_completer/utils.py
action_completer/validator.py
pyproject.toml
prompt_toolkit_action_completer-1.1.1.dist-info/LICENSE
prompt_toolkit_action_completer-1.1.1.dist-info/WHEEL
prompt_toolkit_action_completer-1.1.1.dist-info/METADATA
prompt_toolkit_action_completer-1.1.1.dist-info/RECORD
