Metadata-Version: 2.1
Name: prompt-toolkit-action-completer
Version: 1.1.1
Summary: A fairly simple method for registering callables as prompt-toolkit completions
Home-page: https://github.com/stephen-bunn/prompt-toolkit-action-completer
License: ISC
Keywords: prompt-toolkit,prompt,toolkit,completer,validator,action
Author: Stephen Bunn
Author-email: stephen@bunn.io
Requires-Python: >=3.7,<4.0
Classifier: Development Status :: 4 - Beta
Classifier: Intended Audience :: Developers
Classifier: License :: OSI Approved
Classifier: License :: OSI Approved :: ISC License (ISCL)
Classifier: Natural Language :: English
Classifier: Operating System :: MacOS :: MacOS X
Classifier: Operating System :: Microsoft :: Windows
Classifier: Operating System :: POSIX
Classifier: Programming Language :: Python :: 3
Classifier: Programming Language :: Python :: 3.7
Classifier: Programming Language :: Python :: 3.8
Classifier: Topic :: Software Development :: Libraries :: Python Modules
Provides-Extra: profile
Requires-Dist: attrs (>=20.1.0,<21.0.0)
Requires-Dist: fuzzywuzzy[speedup] (>=0.18.0,<0.19.0)
Requires-Dist: prompt-toolkit (>=3.0.7,<4.0.0)
Requires-Dist: typing-extensions (>=3.7.4,<4.0.0)
Project-URL: Bug Tracker, https://github.com/stephen-bunn/prompt-toolkit-action-completer/issues
Project-URL: Documentation, https://prompt-toolkit-action-completer.readthedocs.io
Project-URL: Repository, https://github.com/stephen-bunn/prompt-toolkit-action-completer
